pd4web/.clang-format
pd4web/.prettierrc
pd4web/.yamlftm
pd4web/Libraries/Libraries.yaml
pd4web/Libraries/ambi~.cmake
pd4web/Libraries/cyclone.cmake
pd4web/Libraries/earplug.cmake
pd4web/Libraries/else.cmake
pd4web/Libraries/libpd.cmake
pd4web/Libraries/o.scofo~.cmake
pd4web/Libraries/pd.cmake/.git
pd4web/Libraries/pd.cmake/.github/workflows/c-cpp.yml
pd4web/Libraries/pd.cmake/.gitignore
pd4web/Libraries/pd.cmake/CMakeLists.txt
pd4web/Libraries/pd.cmake/Examples/.clang-format
pd4web/Libraries/pd.cmake/Examples/CMakeLists.txt
pd4web/Libraries/pd.cmake/Examples/fft~/fft~-help.pd
pd4web/Libraries/pd.cmake/Examples/fft~/fft~.cpp
pd4web/Libraries/pd.cmake/Examples/simple/simple-help.pd
pd4web/Libraries/pd.cmake/Examples/simple/simple-patch.pd
pd4web/Libraries/pd.cmake/Examples/simple/simple.cpp
pd4web/Libraries/pd.cmake/Examples/simple~/simple~-help.pd
pd4web/Libraries/pd.cmake/Examples/simple~/simple~.cpp
pd4web/Libraries/pd.cmake/LICENSE
pd4web/Libraries/pd.cmake/README.md
pd4web/Libraries/pd.cmake/Tests/01.Deprecated-Functions/CMakeLists.txt
pd4web/Libraries/pd.cmake/Tests/CMakeLists.txt
pd4web/Libraries/pd.cmake/pd.cmake
pd4web/Libraries/pmpd.cmake
pd4web/Libraries/timbreIDLib.cmake
pd4web/Templates/1/bula.md
pd4web/Templates/1/index.html
pd4web/Templates/2/index.html
pd4web/Templates/2/sketch.js
pd4web/Templates/3/index.html
pd4web/Templates/4/index.html
pd4web/Templates/4/sketch.js
pd4web/Templates/5/index.html
pd4web/Templates/5/tutorial.md
pd4web/__init__.py
pd4web/cmake-format.yaml
pd4web/config.h
pd4web/externals.cpp
pd4web/favicon.ico
pd4web/index.html
pd4web/nogui.html
pd4web/pd4web/Builder.py
pd4web/pd4web/Compilers.py
pd4web/pd4web/Libraries.py
pd4web/pd4web/Objects.py
pd4web/pd4web/Patch.py
pd4web/pd4web/Pd4Web.py
pd4web/pd4web/__init__.py
pd4web/pd4web.cpp
pd4web/pd4web.gitignore
pd4web/pd4web.gui.js
pd4web/pd4web.hpp
pd4web/pd4web.midi.js
pd4web/pd4web.style.css
pd4web/pd4web.threads.js
pd4web-2.2.7.dist-info/LICENSE
pd4web-2.2.7.dist-info/METADATA
pd4web-2.2.7.dist-info/WHEEL
pd4web-2.2.7.dist-info/entry_points.txt
pd4web-2.2.7.dist-info/RECORD
