Metadata-Version: 2.1
Name: pd4web
Version: 2.2.7
Summary: pd4web compiles PureData patches with external objects for Wasm, allowing to run entire patches in web browsers.
Home-page: https://charlesneimog.github.io/pd4web
Author: Charles K. Neimog
Author-email: charlesneimog@outlook.com
Requires-Python: >=3.9,<4.0
Classifier: Programming Language :: Python :: 3
Classifier: Programming Language :: Python :: 3.9
Classifier: Programming Language :: Python :: 3.10
Classifier: Programming Language :: Python :: 3.11
Classifier: Programming Language :: Python :: 3.12
Classifier: Programming Language :: Python :: 3.13
Requires-Dist: cmake (>=3.21.4,<4.0.0)
Requires-Dist: ninja (>=1.10.2,<2.0.0)
Requires-Dist: pygit2 (>=1.15.1,<2.0.0)
Requires-Dist: pyyaml (>=6.0.0,<7.0.0)
Requires-Dist: requests (>=2.31.0,<3.0.0)
Project-URL: Documentation, https://www.charlesneimog.github.io/pd4web
Project-URL: Repository, https://github.com/charlesneimog/pd4web
